foextract/__init__.py
foextract/extract.py
foextract/mdf.py
foextract/shift.py
foextract/trigger.py
foextract/vbo.py
foextract-0.4.0.dist-info/LICENSE.txt
foextract-0.4.0.dist-info/METADATA
foextract-0.4.0.dist-info/WHEEL
foextract-0.4.0.dist-info/top_level.txt
foextract-0.4.0.dist-info/RECORD
