Metadata-Version: 2.1
Name: foextract
Version: 0.4.0
Summary: Far-Out extract
Home-page: https://gitlab.com/far-out/foextract.git
Author: Jerome Douay
Author-email: jerome@hexamake.com
Platform: any
Classifier: Development Status :: 4 - Beta
Classifier: Programming Language :: Python
License-File: LICENSE.txt
Requires-Dist: progressbar2
Requires-Dist: pandas
Requires-Dist: mdfreader
Requires-Dist: numpy
Requires-Dist: importlib-metadata ; python_version < "3.8"
Provides-Extra: testing
Requires-Dist: setuptools ; extra == 'testing'
Requires-Dist: pytest ; extra == 'testing'
Requires-Dist: pytest-cov ; extra == 'testing'
